MANIFEST.in
README
ffibuilder.py
setup.cfg
setup.py
arepl/__init__.py
arepl/acompile.py
arepl/aeval.py
arepl/astcodeop.py
arepl/help.py
arepl/repl.py
arepl/tests/__init__.py
arepl/tests/test_repl.py
dneio/__init__.py
dneio/concur.py
dneio/core.py
dneio/outcome.py
rsysapps/__init__.py
rsysapps/dnspython_LUA.py
rsysapps/hydra.py
rsysapps/mail.py
rsysapps/miredo.py
rsysapps/powerdns.py
rsyscall/__init__.py
rsyscall/command.py
rsyscall/environ.py
rsyscall/epoller.py
rsyscall/far.py
rsyscall/fcntl.py
rsyscall/inotify_watch.py
rsyscall/limits.py
rsyscall/loader.py
rsyscall/monitor.py
rsyscall/nix.py
rsyscall/path.py
rsyscall/sched.py
rsyscall/signal.py
rsyscall/struct.py
rsyscall/thread.py
rsyscall/time.py
rsyscall/wish.py
rsyscall.egg-info/PKG-INFO
rsyscall.egg-info/SOURCES.txt
rsyscall.egg-info/dependency_links.txt
rsyscall.egg-info/top_level.txt
rsyscall/doc/__init__.py
rsyscall/doc/syscall_api.py
rsyscall/handle/__init__.py
rsyscall/handle/fd.py
rsyscall/handle/pointer.py
rsyscall/handle/process.py
rsyscall/linux/__init__.py
rsyscall/linux/dirent.py
rsyscall/linux/fuse.py
rsyscall/linux/futex.py
rsyscall/linux/memfd.py
rsyscall/linux/netlink.py
rsyscall/linux/rtnetlink.py
rsyscall/memory/__init__.py
rsyscall/memory/allocation_interface.py
rsyscall/memory/allocator.py
rsyscall/memory/ram.py
rsyscall/memory/socket_transport.py
rsyscall/memory/transport.py
rsyscall/near/__init__.py
rsyscall/near/sysif.py
rsyscall/near/types.py
rsyscall/net/__init__.py
rsyscall/net/if_.py
rsyscall/netinet/__init__.py
rsyscall/netinet/in_.py
rsyscall/netinet/ip.py
rsyscall/netinet/tcp.py
rsyscall/network/__init__.py
rsyscall/network/connection.py
rsyscall/scripts/__init__.py
rsyscall/scripts/local_repl.py
rsyscall/scripts/symsh.py
rsyscall/stdlib/__init__.py
rsyscall/stdlib/mktemp.py
rsyscall/sys/__init__.py
rsyscall/sys/capability.py
rsyscall/sys/epoll.py
rsyscall/sys/eventfd.py
rsyscall/sys/inotify.py
rsyscall/sys/ioctl.py
rsyscall/sys/mman.py
rsyscall/sys/mount.py
rsyscall/sys/prctl.py
rsyscall/sys/resource.py
rsyscall/sys/signalfd.py
rsyscall/sys/socket.py
rsyscall/sys/stat.py
rsyscall/sys/syscall.py
